sopel_respects/__init__.py
sopel_respects/plugin.py
sopel_respects-1.0.0.dist-info/LICENSE
sopel_respects-1.0.0.dist-info/METADATA
sopel_respects-1.0.0.dist-info/WHEEL
sopel_respects-1.0.0.dist-info/entry_points.txt
sopel_respects-1.0.0.dist-info/top_level.txt
sopel_respects-1.0.0.dist-info/RECORD
