Metadata-Version: 2.1
Name: sopel-respects
Version: 1.0.0
Summary: Press F to pay respects.
Author-email: xnaas <me@xnaas.info>
Maintainer-email: dgw <dgw@technobabbl.es>
License: The Unlicense
Project-URL: Homepage, https://github.com/dgw/sopel-respects
Project-URL: Bug Tracker, https://github.com/dgw/sopel-respects/issues
Platform: Linux x86, x86-64
Classifier: Development Status :: 5 - Production/Stable
Classifier: License :: OSI Approved :: The Unlicense (Unlicense)
Classifier: Operating System :: POSIX :: Linux
Classifier: Programming Language :: Python :: 3.8
Classifier: Programming Language :: Python :: 3.9
Classifier: Programming Language :: Python :: 3.10
Classifier: Programming Language :: Python :: 3.11
Classifier: Programming Language :: Python :: 3.12
Classifier: Programming Language :: Python :: 3 :: Only
Classifier: Topic :: Communications :: Chat :: Internet Relay Chat
Requires-Python: <4,>=3.8
License-File: LICENSE
Requires-Dist: sopel>=7.1
